file_finder/cli.py
file_finder/constants.py
file_finder/exceptions.py
file_finder/finder.py
file_finder/utils.py
finderfilepath-0.1.2.dist-info/METADATA
finderfilepath-0.1.2.dist-info/WHEEL
finderfilepath-0.1.2.dist-info/entry_points.txt
finderfilepath-0.1.2.dist-info/RECORD
