Metadata-Version: 2.1
Name: finderfilepath
Version: 0.1.2
Summary: Filehound é uma ferramenta de busca de arquivos para sistemas operacionais desenvolvida em Python.
Author: Dgeison
Author-email: dgeison.peixoto@gmail.com
Requires-Python: >=3.10,<4.0
Classifier: Programming Language :: Python :: 3
Classifier: Programming Language :: Python :: 3.10
Classifier: Programming Language :: Python :: 3.11
Classifier: Programming Language :: Python :: 3.12
Requires-Dist: click (>=8.1.7,<9.0.0)
Requires-Dist: tabulate (>=0.9.0,<0.10.0)
